CHANGELOG.md
README.md
stockpyl/__init__.py
stockpyl/aux_files/named_instances.csv
stockpyl/demand_source.py
stockpyl/disruption_process.py
stockpyl/eoq.py
stockpyl/finite_horizon.py
stockpyl/gsm_helpers.py
stockpyl/gsm_serial.py
stockpyl/gsm_tree.py
stockpyl/helpers.py
stockpyl/instances.py
stockpyl/loss_functions.py
stockpyl/meio_general.py
stockpyl/newsvendor.py
stockpyl/optimization.py
stockpyl/policy.py
stockpyl/rq.py
stockpyl/sim.py
stockpyl/sim_io.py
stockpyl/ss.py
stockpyl/ssm_serial.py
stockpyl/supply_chain_network.py
stockpyl/supply_chain_node.py
stockpyl/supply_uncertainty.py
stockpyl/wagner_whitin.py
test_stockpyl-0.0.9.dist-info/LICENSE
test_stockpyl-0.0.9.dist-info/WHEEL
test_stockpyl-0.0.9.dist-info/METADATA
test_stockpyl-0.0.9.dist-info/RECORD
