Metadata-Version: 2.1
Name: test-stockpyl
Version: 0.0.9
Summary: Python inventory optimization tools.
Home-page: https://github.com/LarrySnyder/stockpyl
License: GNU Version 3
Keywords: inventory management,orms
Author: Alex Kressner
Requires-Python: >=3.8,<3.11
Classifier: License :: Other/Proprietary License
Classifier: Programming Language :: Python :: 3
Classifier: Programming Language :: Python :: 3.10
Classifier: Programming Language :: Python :: 3.8
Classifier: Programming Language :: Python :: 3.9
Requires-Dist: jsonpickle (==2.2.0)
Requires-Dist: matplotlib (==3.5.2)
Requires-Dist: networkx (==2.8.2)
Requires-Dist: numpy (==1.22.4)
Requires-Dist: scipy (>=1.8.1,<2.0.0)
Requires-Dist: sphinx_rtd_theme (==1.0.0)
Requires-Dist: tabulate (==0.8.9)
Requires-Dist: tqdm (==4.64.0)
Project-URL: Documentation, http://stockpyl.readthedocs.io
Project-URL: Repository, https://github.com/LarrySnyder/stockpyl
